http_prompt/__init__.py
http_prompt/cli.py
http_prompt/completer.py
http_prompt/completion.py
http_prompt/config.py
http_prompt/constants.py
http_prompt/contextio.py
http_prompt/defaultconfig.py
http_prompt/execution.py
http_prompt/jsonfilecompleter.py
http_prompt/jsonfilehistory.py
http_prompt/lexer.py
http_prompt/options.py
http_prompt/output.py
http_prompt/projectcollect.py
http_prompt/projectcompleter.py
http_prompt/projectconfig.py
http_prompt/tree.py
http_prompt/utils.py
http_prompt/xdg.py
http_prompt/context/__init__.py
http_prompt/context/transform.py
whale_http-1.0.1.dist-info/METADATA
whale_http-1.0.1.dist-info/WHEEL
whale_http-1.0.1.dist-info/entry_points.txt
whale_http-1.0.1.dist-info/top_level.txt
whale_http-1.0.1.dist-info/RECORD
