Metadata-Version: 2.1
Name: whale-http
Version: 1.0.1
Summary: Fork from http-prompt(2.1.0), add ability of project manage.
Home-page: https://github.com/yuexl/whale-http
Author: dajing
Author-email: yueblagon@gmail.com
License: MIT
Classifier: Development Status :: 3 - Alpha
Classifier: Environment :: Console
Classifier: Intended Audience :: Developers
Classifier: Intended Audience :: System Administrators
Classifier: License :: OSI Approved :: MIT License
Classifier: Topic :: Internet :: WWW/HTTP
Classifier: Topic :: Software Development
Classifier: Topic :: System :: Networking
Classifier: Topic :: Terminals
Classifier: Operating System :: OS Independent
Classifier: Programming Language :: Python
Classifier: Programming Language :: Python :: 3.8
Requires-Dist: click (>=5.0)
Requires-Dist: httpie (>=2.5.0)
Requires-Dist: parsimonious (>=0.6.2)
Requires-Dist: prompt-toolkit (<3.0.0,>=2.0.0)
Requires-Dist: Pygments (>=2.1.0)
Requires-Dist: PyYAML (>=3.0)
Requires-Dist: pydantic (==2.1.1)
Requires-Dist: pydantic-core (==2.4.0) ; python_version >= "3.7"
